ha_mqtt_discoverable_cli/__init__.py
ha_mqtt_discoverable_cli/cli.py
ha_mqtt_discoverable_cli/device.py
ha_mqtt_discoverable_cli/device_driver.py
ha_mqtt_discoverable_cli/hmd.py
ha_mqtt_discoverable_cli/sensor_driver.py
ha_mqtt_discoverable_cli/settings.py
ha_mqtt_discoverable_cli/utils.py
ha_mqtt_discoverable_cli-0.23.0.dist-info/METADATA
ha_mqtt_discoverable_cli-0.23.0.dist-info/WHEEL
ha_mqtt_discoverable_cli-0.23.0.dist-info/entry_points.txt
ha_mqtt_discoverable_cli-0.23.0.dist-info/licenses/LICENSE
ha_mqtt_discoverable_cli-0.23.0.dist-info/RECORD
