Metadata-Version: 2.4
Name: ha-mqtt-discoverable-cli
Version: 0.23.0
Summary: CLI tools for the ha-mqtt-discoverable module
License: Apache 2.0
License-File: LICENSE
Author: Joe Block
Author-email: jpb@unixorn.net
Requires-Python: >=3.10,<4.0.0
Classifier: License :: Other/Proprietary License
Classifier: Programming Language :: Python :: 3
Classifier: Programming Language :: Python :: 3.10
Classifier: Programming Language :: Python :: 3.11
Classifier: Programming Language :: Python :: 3.12
Classifier: Programming Language :: Python :: 3.13
Classifier: Programming Language :: Python :: 3.14
Requires-Dist: gitlike-commands (>=0.3.0,<0.4.0)
Requires-Dist: ha-mqtt-discoverable (>=0.23.0,<0.24.0)
